Metadata-Version: 1.0
Name: dap.plugins.hdf5
Version: 0.1dev-r305
Summary: HDF5 plugin for pydap server based on Pytables
Home-page: http://pydap.org/plugins/hdf5.html
Author: Roberto De Almeida
Author-email: rob@pydap.org
License: MIT
Keywords: hdf5 pytables dap opendap dods data
Platform: UNKNOWN
Classifier: Development Status :: 4 - Beta
Classifier: Environment :: Console
Classifier: Intended Audience :: Developers
Classifier: Intended Audience :: Science/Research
Classifier: License :: OSI Approved :: MIT License
Classifier: Operating System :: OS Independent
Classifier: Programming Language :: Python
Classifier: Topic :: Internet
Classifier: Topic :: Scientific/Engineering
Classifier: Topic :: Software Development :: Libraries :: Python Modules
